yta_stock_pexels/__init__.py
yta_stock_pexels/api.py
yta_stock_pexels/dataclasses.py
yta_stock_pexels/enum.py
yta_stock_pexels/settings.py
yta_stock_pexels-0.0.1.dist-info/licenses/LICENSE
yta_stock_pexels-0.0.1.dist-info/METADATA
yta_stock_pexels-0.0.1.dist-info/WHEEL
yta_stock_pexels-0.0.1.dist-info/RECORD
